dash_panels/GroupPanel.py
dash_panels/Panel.py
dash_panels/PanelGroup.py
dash_panels/PanelResizeHandle.py
dash_panels/ResizableModal.py
dash_panels/__init__.py
dash_panels/_imports_.py
dash_panels/dash_panels.min.js
dash_panels/dash_panels.min.js.map
dash_panels/metadata.json
dash_panels/package-info.json
dash_panels-0.0.4.dist-info/licenses/LICENSE
dash_panels-0.0.4.dist-info/METADATA
dash_panels-0.0.4.dist-info/WHEEL
dash_panels-0.0.4.dist-info/top_level.txt
dash_panels-0.0.4.dist-info/RECORD
