Metadata-Version: 2.4
Name: dash_panels
Version: 0.0.4
Summary: Resizable panels inspired by react-resizable-panels.
Author: Evan Rasmussen <evanras@umich.edu>
License: MIT
Classifier: Framework :: Dash
License-File: LICENSE
Dynamic: author
Dynamic: classifier
Dynamic: description
Dynamic: description-content-type
Dynamic: license
Dynamic: license-file
Dynamic: summary
